metaMATE-0.2b6.data/scripts/maketree.R
metamate/__init__.py
metamate/binning.py
metamate/core.py
metamate/filterlength.py
metamate/filterreference.py
metamate/filtertranslate.py
metamate/getclades.R
metamate/maketree.R
metamate/metamate.py
metaMATE-0.2b6.dist-info/LICENSE
metaMATE-0.2b6.dist-info/METADATA
metaMATE-0.2b6.dist-info/WHEEL
metaMATE-0.2b6.dist-info/entry_points.txt
metaMATE-0.2b6.dist-info/top_level.txt
metaMATE-0.2b6.dist-info/RECORD
