Metadata-Version: 2.1
Name: metaMATE
Version: 0.2b6
Summary: metaMATE: validated removal of pseudogenes and sequencing artefacts for mitochondrial metabarcoding
Home-page: https://github.com/tjcreedy/metamate
Author: Thomas J. Creedy
Author-email: thomas.creedy@gmail.com
License: UNKNOWN
Platform: UNKNOWN
Classifier: Programming Language :: Python :: 3
Classifier: Programming Language :: R
Classifier: License :: OSI Approved :: GNU General Public License (GPL)
Classifier: Development Status :: 4 - Beta
Classifier: Environment :: Console
Classifier: Intended Audience :: Science/Research
Classifier: Operating System :: OS Independent
Classifier: Topic :: Scientific/Engineering :: Bio-Informatics
Requires-Python: >=3.6
Requires-Dist: biopython (>=1.76)
Requires-Dist: scipy (>=1.4.1)
